cached_sentence_transformer/__init__.py
cached_sentence_transformer/cache.py
cached_sentence_transformer/hashing.py
cached_sentence_transformer/identifiers.py
cached_sentence_transformer/postgres_kv_store.py
cached_sentence_transformer/vectors.py
cached_sentence_transformer-0.1.0.dist-info/licenses/LICENSE
cached_sentence_transformer-0.1.0.dist-info/METADATA
cached_sentence_transformer-0.1.0.dist-info/WHEEL
cached_sentence_transformer-0.1.0.dist-info/top_level.txt
cached_sentence_transformer-0.1.0.dist-info/RECORD
