Metadata-Version: 2.4
Name: cached-sentence-transformer
Version: 0.1.0
Summary: PostgreSQL-backed embedding cache for SentenceTransformers
License: MIT License
Project-URL: Homepage, https://github.com/prasanna/cached-sentence-transformer
Project-URL: Repository, https://github.com/prasanna/cached-sentence-transformer
Project-URL: Issues, https://github.com/prasanna/cached-sentence-transformer/issues
Keywords: embeddings,nlp,sentence-transformers,postgres,cache
Classifier: Development Status :: 3 - Alpha
Classifier: Intended Audience :: Developers
Classifier: License :: OSI Approved :: MIT License
Classifier: Programming Language :: Python :: 3
Classifier: Programming Language :: Python :: 3 :: Only
Classifier: Programming Language :: Python :: 3.10
Classifier: Programming Language :: Python :: 3.11
Classifier: Programming Language :: Python :: 3.12
Classifier: Topic :: Scientific/Engineering :: Artificial Intelligence
Requires-Python: >=3.10
License-File: LICENSE
Requires-Dist: numpy>=1.23
Requires-Dist: torch
Requires-Dist: sentence-transformers>=2.2
Requires-Dist: psycopg2-binary>=2.9
Requires-Dist: tqdm>=4.60
Requires-Dist: python-dotenv>=1.0
Provides-Extra: dev
Requires-Dist: pytest>=7.0; extra == "dev"
Requires-Dist: pytest-cov>=4.0; extra == "dev"
Requires-Dist: ruff>=0.6.0; extra == "dev"
Requires-Dist: build>=1.0; extra == "dev"
Requires-Dist: twine>=5.0; extra == "dev"
Dynamic: license-file
